{
"#/stdaS": "{^}/{^}",
"*d": "{^'d}",
"-ndg": "{^~|\"}",
"-tdS": "{^}\\}",
"-tdSg": "{^}]",
"-tdg": "{^})",
"a*It": "{^_}",
"aIt": "{_^}",
"bd*dg": "{^,^}",
"bd-dg": "{,}",
"bd-tS": "{?}",
"bd-tS/pt-dg": "{^}‽",
"bd-tdSg": "{:}",
"bdr": "{~|\"^}",
"bdr-ndg": "{^ -- ^}",
"btaeIUftS": ". o O ({^}{-|}",
"pa*Und": "£{^}",
"pb": "{-|}",
"pbtd": "[{^}",
"pbtd*tdSg": "{^...}{-|}",
"pbtd-dg": "{;}",
"pbtd-tdSg": "{^…}{ }{-|}",
"pbw*l": "=",
"pt*tS": "{^.^}",
"pt-dg": "{!}",
"pt-dg/bd-tS": "{^}‽",
"pt-tS": "{.}",
"ptwa*S": "#",
"r*n": "{#Return}{^}",
"r-n": "{^~|\n^}",
"sp": "{^}",
"spb": "{^}{-|}",
"ta*ftS": "{^\t^}"
}
